[
    {
        "word_id": "word_man",
        "hebrew": "אִישׁ",
        "english": "man",
        "ukrainian": "чоловік",
        "transcription": "ish",
        "correct": 0,
        "wrong": 0,
        "last_correct": false,
        "writing_correct": 0,
        "writing_wrong": 0,
        "writing_last_correct": false
    },
    {
        "word_id": "word_woman",
        "hebrew": "אִשָּׁה",
        "english": "woman",
        "ukrainian": "жінка",
        "transcription": "isha",
        "correct": 0,
        "wrong": 0,
        "last_correct": false,
        "writing_correct": 0,
        "writing_wrong": 0,
        "writing_last_correct": false
    },
    {
        "word_id": "word_child",
        "hebrew": "יֶלֶד",
        "english": "child",
        "ukrainian": "дитина",
        "transcription": "yeled",
        "correct": 1,
        "wrong": 0,
        "last_correct": false,
        "writing_correct": 0,
        "writing_wrong": 0,
        "writing_last_correct": false
    },
    {
        "word_id": "word_tree",
        "hebrew": "עֵץ",
        "english": "tree",
        "ukrainian": "дерево",
        "transcription": "etz",
        "correct": 0,
        "wrong": 0,
        "last_correct": false,
        "writing_correct": 0,
        "writing_wrong": 0,
        "writing_last_correct": false
    },
    {
        "word_id": "word_book",
        "hebrew": "סֵפֶר",
        "english": "book",
        "ukrainian": "книга",
        "transcription": "sefer",
        "correct": 0,
        "wrong": 0,
        "last_correct": false,
        "writing_correct": 0,
        "writing_wrong": 0,
        "writing_last_correct": false
    },
    {
        "word_id": "word_house",
        "hebrew": "בַּיִת",
        "english": "house",
        "ukrainian": "будинок",
        "transcription": "bayit",
        "correct": 1,
        "wrong": 0,
        "last_correct": false,
        "writing_correct": 0,
        "writing_wrong": 0,
        "writing_last_correct": false
    },
    {
        "word_id": "word_car",
        "hebrew": "מְכוֹנִית",
        "english": "car",
        "ukrainian": "автомобіль",
        "transcription": "mekhonit",
        "correct": 0,
        "wrong": 0,
        "last_correct": false,
        "writing_correct": 0,
        "writing_wrong": 0,
        "writing_last_correct": false
    },
    {
        "word_id": "word_city",
        "hebrew": "עִיר",
        "english": "city",
        "ukrainian": "місто",
        "transcription": "ir",
        "correct": 1,
        "wrong": 0,
        "last_correct": false,
        "writing_correct": 0,
        "writing_wrong": 0,
        "writing_last_correct": false
    },
    {
        "word_id": "word_country",
        "hebrew": "מְדִינָה",
        "english": "country",
        "ukrainian": "країна",
        "transcription": "medina",
        "correct": 1,
        "wrong": 0,
        "last_correct": false,
        "writing_correct": 0,
        "writing_wrong": 0,
        "writing_last_correct": false
    },
    {
        "word_id": "word_fish",
        "hebrew": "דָּג",
        "english": "fish",
        "ukrainian": "риба",
        "transcription": "dag",
        "correct": 2,
        "wrong": 0,
        "last_correct": false,
        "writing_correct": 0,
        "writing_wrong": 0,
        "writing_last_correct": false
    },
    {
        "word_id": "word_dog",
        "hebrew": "כֶּלֶב",
        "english": "dog",
        "ukrainian": "собака",
        "transcription": "kelev",
        "correct": 0,
        "wrong": 0,
        "last_correct": false,
        "writing_correct": 0,
        "writing_wrong": 0,
        "writing_last_correct": false
    },
    {
        "word_id": "word_cat",
        "hebrew": "חָתוּל",
        "english": "cat",
        "ukrainian": "кіт",
        "transcription": "khatul",
        "correct": 1,
        "wrong": 0,
        "last_correct": false,
        "writing_correct": 0,
        "writing_wrong": 0,
        "writing_last_correct": false
    },
    {
        "word_id": "word_computer",
        "hebrew": "מַחְשֵׁב",
        "english": "computer",
        "ukrainian": "комп'ютер",
        "transcription": "makhshav",
        "correct": 2,
        "wrong": 0,
        "last_correct": false,
        "writing_correct": 0,
        "writing_wrong": 0,
        "writing_last_correct": false
    },
    {
        "word_id": "word_chair",
        "hebrew": "כִּיסֵּא",
        "english": "chair",
        "ukrainian": "стілець",
        "transcription": "kise",
        "correct": 1,
        "wrong": 0,
        "last_correct": false,
        "writing_correct": 0,
        "writing_wrong": 0,
        "writing_last_correct": false
    },
    {
        "word_id": "word_table",
        "hebrew": "שֻׁלְחָן",
        "english": "table",
        "ukrainian": "стіл",
        "transcription": "shulchan",
        "correct": 1,
        "wrong": 0,
        "last_correct": false,
        "writing_correct": 0,
        "writing_wrong": 0,
        "writing_last_correct": false
    },
    {
        "word_id": "word_apple",
        "hebrew": "תַּפּוּחַ",
        "english": "apple",
        "ukrainian": "яблуко",
        "transcription": "tapuach",
        "correct": 1,
        "wrong": 0,
        "last_correct": false,
        "writing_correct": 0,
        "writing_wrong": 0,
        "writing_last_correct": false
    },
    {
        "word_id": "word_water",
        "hebrew": "מַיִם",
        "english": "water",
        "ukrainian": "вода",
        "transcription": "mayim",
        "correct": 0,
        "wrong": 0,
        "last_correct": false,
        "writing_correct": 0,
        "writing_wrong": 0,
        "writing_last_correct": false
    },
    {
        "word_id": "word_flower",
        "hebrew": "פֶּרַח",
        "english": "flower",
        "ukrainian": "квітка",
        "transcription": "perach",
        "correct": 3,
        "wrong": 0,
        "last_correct": false,
        "writing_correct": 0,
        "writing_wrong": 0,
        "writing_last_correct": false
    },
    {
        "word_id": "word_phone",
        "hebrew": "טֵלֵפוֹן",
        "english": "phone",
        "ukrainian": "телефон",
        "transcription": "telefon",
        "correct": 1,
        "wrong": 0,
        "last_correct": false,
        "writing_correct": 0,
        "writing_wrong": 0,
        "writing_last_correct": false
    },
    {
        "word_id": "word_door",
        "hebrew": "דֶּלֶת",
        "english": "door",
        "ukrainian": "двері",
        "transcription": "delet",
        "correct": 2,
        "wrong": 0,
        "last_correct": false,
        "writing_correct": 0,
        "writing_wrong": 0,
        "writing_last_correct": false
    },
    {
        "word_id": "word_window",
        "hebrew": "חַלּוֹן",
        "english": "window",
        "ukrainian": "вікно",
        "transcription": "chalon",
        "correct": 2,
        "wrong": 0,
        "last_correct": false,
        "writing_correct": 0,
        "writing_wrong": 0,
        "writing_last_correct": false
    },
    {
        "word_id": "word_newspaper",
        "hebrew": "עִיתּוֹן",
        "english": "newspaper",
        "ukrainian": "газета",
        "transcription": "iton",
        "correct": 1,
        "wrong": 0,
        "last_correct": false,
        "writing_correct": 0,
        "writing_wrong": 0,
        "writing_last_correct": false
    },
    {
        "word_id": "word_key",
        "hebrew": "מַפְתֵּחַ",
        "english": "key",
        "ukrainian": "ключ",
        "transcription": "mafteach",
        "correct": 0,
        "wrong": 0,
        "last_correct": false,
        "writing_correct": 0,
        "writing_wrong": 0,
        "writing_last_correct": false
    },
    {
        "word_id": "word_television",
        "hebrew": "טֶלֶוִיזְיָה",
        "english": "television",
        "ukrainian": "телевізор",
        "transcription": "televizia",
        "correct": 1,
        "wrong": 0,
        "last_correct": false,
        "writing_correct": 0,
        "writing_wrong": 0,
        "writing_last_correct": false
    },
    {
        "word_id": "word_street",
        "hebrew": "רְחוֹב",
        "english": "street",
        "ukrainian": "вулиця",
        "transcription": "rechov",
        "correct": 0,
        "wrong": 0,
        "last_correct": false,
        "writing_correct": 0,
        "writing_wrong": 0,
        "writing_last_correct": false
    },
    {
        "word_id": "word_weather",
        "hebrew": "מֶזֶג אֲוִיר",
        "english": "weather",
        "ukrainian": "погода",
        "transcription": "mezeg avir",
        "correct": 1,
        "wrong": 0,
        "last_correct": false,
        "writing_correct": 0,
        "writing_wrong": 0,
        "writing_last_correct": false
    },
    {
        "word_id": "word_sun",
        "hebrew": "שֶׁמֶשׁ",
        "english": "sun",
        "ukrainian": "сонце",
        "transcription": "shemesh",
        "correct": 2,
        "wrong": 0,
        "last_correct": false,
        "writing_correct": 0,
        "writing_wrong": 0,
        "writing_last_correct": false
    },
    {
        "word_id": "word_moon",
        "hebrew": "יָרֵחַ",
        "english": "moon",
        "ukrainian": "місяць",
        "transcription": "yareach",
        "correct": 1,
        "wrong": 0,
        "last_correct": false,
        "writing_correct": 0,
        "writing_wrong": 0,
        "writing_last_correct": false
    },
    {
        "word_id": "word_star",
        "hebrew": "כּוֹכָב",
        "english": "star",
        "ukrainian": "зірка",
        "transcription": "kochav",
        "correct": 0,
        "wrong": 0,
        "last_correct": false,
        "writing_correct": 0,
        "writing_wrong": 0,
        "writing_last_correct": false
    },
    {
        "word_id": "word_food",
        "hebrew": "אוֹכֶל",
        "english": "food",
        "ukrainian": "їжа",
        "transcription": "ochel",
        "correct": 0,
        "wrong": 0,
        "last_correct": false,
        "writing_correct": 0,
        "writing_wrong": 0,
        "writing_last_correct": false
    },
    {
        "word_id": "word_drink",
        "hebrew": "שְׁתִיָּה",
        "english": "drink",
        "ukrainian": "напій",
        "transcription": "shtiya",
        "correct": 0,
        "wrong": 0,
        "last_correct": false,
        "writing_correct": 0,
        "writing_wrong": 0,
        "writing_last_correct": false
    },
    {
        "word_id": "word_restaurant",
        "hebrew": "מִסְעָדָה",
        "english": "restaurant",
        "ukrainian": "ресторан",
        "transcription": "misada",
        "correct": 2,
        "wrong": 0,
        "last_correct": false,
        "writing_correct": 0,
        "writing_wrong": 0,
        "writing_last_correct": false
    },
    {
        "word_id": "word_school",
        "hebrew": "בֵּית סֵפֶר",
        "english": "school",
        "ukrainian": "школа",
        "transcription": "beit sefer",
        "correct": 2,
        "wrong": 0,
        "last_correct": false,
        "writing_correct": 0,
        "writing_wrong": 0,
        "writing_last_correct": false
    },
    {
        "word_id": "word_university",
        "hebrew": "אוּנִיבֶרְסִיטָה",
        "english": "university",
        "ukrainian": "університет",
        "transcription": "universita",
        "correct": 0,
        "wrong": 0,
        "last_correct": false,
        "writing_correct": 0,
        "writing_wrong": 0,
        "writing_last_correct": false
    },
    {
        "word_id": "word_teacher",
        "hebrew": "מוֹרֶה",
        "english": "teacher",
        "ukrainian": "вчитель",
        "transcription": "more",
        "correct": 2,
        "wrong": 1,
        "last_correct": false,
        "writing_correct": 0,
        "writing_wrong": 1,
        "writing_last_correct": false
    },
    {
        "word_id": "word_student",
        "hebrew": "תַּלְמִיד",
        "english": "student",
        "ukrainian": "студент",
        "transcription": "talmid",
        "correct": 0,
        "wrong": 0,
        "last_correct": false,
        "writing_correct": 0,
        "writing_wrong": 0,
        "writing_last_correct": false
    },
    {
        "word_id": "word_doctor",
        "hebrew": "רוֹפֵא",
        "english": "doctor",
        "ukrainian": "лікар",
        "transcription": "rofe",
        "correct": 3,
        "wrong": 0,
        "last_correct": false,
        "writing_correct": 0,
        "writing_wrong": 0,
        "writing_last_correct": false
    },
    {
        "word_id": "word_nurse",
        "hebrew": "אָחוֹת",
        "english": "nurse",
        "ukrainian": "медсестра",
        "transcription": "achot",
        "correct": 1,
        "wrong": 0,
        "last_correct": false,
        "writing_correct": 0,
        "writing_wrong": 0,
        "writing_last_correct": false
    },
    {
        "word_id": "word_hospital",
        "hebrew": "בֵּית חוֹלִים",
        "english": "hospital",
        "ukrainian": "лікарня",
        "transcription": "beit cholim",
        "correct": 0,
        "wrong": 0,
        "last_correct": false,
        "writing_correct": 0,
        "writing_wrong": 0,
        "writing_last_correct": false
    },
    {
        "word_id": "word_medicine",
        "hebrew": "תְּרוּפָה",
        "english": "medicine",
        "ukrainian": "ліки",
        "transcription": "trufa",
        "correct": 1,
        "wrong": 1,
        "last_correct": false,
        "writing_correct": 0,
        "writing_wrong": 0,
        "writing_last_correct": false
    },
    {
        "word_id": "word_park",
        "hebrew": "פַּארְק",
        "english": "park",
        "ukrainian": "парк",
        "transcription": "park",
        "correct": 0,
        "wrong": 0,
        "last_correct": false,
        "writing_correct": 0,
        "writing_wrong": 0,
        "writing_last_correct": false
    },
    {
        "word_id": "word_game",
        "hebrew": "מִשְׂחָק",
        "english": "game",
        "ukrainian": "гра",
        "transcription": "mis'chak",
        "correct": 1,
        "wrong": 0,
        "last_correct": false,
        "writing_correct": 0,
        "writing_wrong": 0,
        "writing_last_correct": false
    },
    {
        "word_id": "word_sport",
        "hebrew": "סְפּוֹרְט",
        "english": "sport",
        "ukrainian": "спорт",
        "transcription": "sport",
        "correct": 1,
        "wrong": 0,
        "last_correct": false,
        "writing_correct": 0,
        "writing_wrong": 0,
        "writing_last_correct": false
    },
    {
        "word_id": "word_ball",
        "hebrew": "כַּדּוּר",
        "english": "ball",
        "ukrainian": "м'яч",
        "transcription": "kadur",
        "correct": 2,
        "wrong": 0,
        "last_correct": false,
        "writing_correct": 0,
        "writing_wrong": 0,
        "writing_last_correct": false
    },
    {
        "word_id": "word_hour",
        "hebrew": "שָׁעָה",
        "english": "hour",
        "ukrainian": "година",
        "transcription": "sha'a",
        "correct": 0,
        "wrong": 0,
        "last_correct": false,
        "writing_correct": 0,
        "writing_wrong": 0,
        "writing_last_correct": false
    },
    {
        "word_id": "word_minute",
        "hebrew": "דַּקָּה",
        "english": "minute",
        "ukrainian": "хвилина",
        "transcription": "daka",
        "correct": 1,
        "wrong": 0,
        "last_correct": false,
        "writing_correct": 0,
        "writing_wrong": 0,
        "writing_last_correct": false
    },
    {
        "word_id": "word_second",
        "hebrew": "שְׁנִיָּה",
        "english": "second",
        "ukrainian": "секунда",
        "transcription": "shniya",
        "correct": 0,
        "wrong": 0,
        "last_correct": false,
        "writing_correct": 0,
        "writing_wrong": 0,
        "writing_last_correct": false
    },
    {
        "word_id": "word_year",
        "hebrew": "שָׁנָה",
        "english": "year",
        "ukrainian": "рік",
        "transcription": "shana",
        "correct": 1,
        "wrong": 0,
        "last_correct": false,
        "writing_correct": 0,
        "writing_wrong": 0,
        "writing_last_correct": false
    },
    {
        "word_id": "word_mother",
        "hebrew": "אֵם",
        "english": "mother",
        "ukrainian": "мати",
        "transcription": "em",
        "correct": 0,
        "wrong": 0,
        "last_correct": false,
        "writing_correct": 0,
        "writing_wrong": 0,
        "writing_last_correct": false
    },
    {
        "word_id": "word_father",
        "hebrew": "אָב",
        "english": "father",
        "ukrainian": "батько",
        "transcription": "av",
        "correct": 0,
        "wrong": 0,
        "last_correct": false,
        "writing_correct": 0,
        "writing_wrong": 0,
        "writing_last_correct": false
    },
    {
        "word_id": "word_boy",
        "hebrew": "בֵּן",
        "english": "boy",
        "ukrainian": "хлопець",
        "transcription": "ben",
        "correct": 0,
        "wrong": 0,
        "last_correct": false,
        "writing_correct": 0,
        "writing_wrong": 0,
        "writing_last_correct": false
    },
    {
        "word_id": "word_girl",
        "hebrew": "יַלְדָּה",
        "english": "girl",
        "ukrainian": "дівчина",
        "transcription": "yalda",
        "correct": 0,
        "wrong": 0,
        "last_correct": false,
        "writing_correct": 0,
        "writing_wrong": 0,
        "writing_last_correct": false
    },
    {
        "word_id": "word_family",
        "hebrew": "מִשְׁפָּחָה",
        "english": "family",
        "ukrainian": "родина",
        "transcription": "mishpakha",
        "correct": 0,
        "wrong": 0,
        "last_correct": false,
        "writing_correct": 0,
        "writing_wrong": 0,
        "writing_last_correct": false
    },
    {
        "word_id": "word_friend",
        "hebrew": "חָבֵר",
        "english": "friend",
        "ukrainian": "друг",
        "transcription": "khaver",
        "correct": 0,
        "wrong": 0,
        "last_correct": false,
        "writing_correct": 0,
        "writing_wrong": 0,
        "writing_last_correct": false
    },
    {
        "word_id": "word_person",
        "hebrew": "אָדָם",
        "english": "person",
        "ukrainian": "людина",
        "transcription": "adam",
        "correct": 0,
        "wrong": 0,
        "last_correct": false,
        "writing_correct": 0,
        "writing_wrong": 0,
        "writing_last_correct": false
    },
    {
        "word_id": "word_day",
        "hebrew": "יוֹם",
        "english": "day",
        "ukrainian": "день",
        "transcription": "yom",
        "correct": 0,
        "wrong": 0,
        "last_correct": false,
        "writing_correct": 0,
        "writing_wrong": 0,
        "writing_last_correct": false
    },
    {
        "word_id": "word_night",
        "hebrew": "לַיְלָה",
        "english": "night",
        "ukrainian": "ніч",
        "transcription": "layla",
        "correct": 0,
        "wrong": 0,
        "last_correct": false,
        "writing_correct": 0,
        "writing_wrong": 0,
        "writing_last_correct": false
    },
    {
        "word_id": "word_morning",
        "hebrew": "בֹּקֶר",
        "english": "morning",
        "ukrainian": "ранок",
        "transcription": "boker",
        "correct": 0,
        "wrong": 0,
        "last_correct": false,
        "writing_correct": 0,
        "writing_wrong": 0,
        "writing_last_correct": false
    },
    {
        "word_id": "word_evening",
        "hebrew": "עֶרֶב",
        "english": "evening",
        "ukrainian": "вечір",
        "transcription": "erev",
        "correct": 0,
        "wrong": 0,
        "last_correct": false,
        "writing_correct": 0,
        "writing_wrong": 0,
        "writing_last_correct": false
    },
    {
        "word_id": "word_week",
        "hebrew": "שָׁבוּעַ",
        "english": "week",
        "ukrainian": "тиждень",
        "transcription": "shavua",
        "correct": 0,
        "wrong": 0,
        "last_correct": false,
        "writing_correct": 0,
        "writing_wrong": 0,
        "writing_last_correct": false
    },
    {
        "word_id": "word_month",
        "hebrew": "חוֹדֶשׁ",
        "english": "month",
        "ukrainian": "місяць (період)",
        "transcription": "chodesh",
        "correct": 0,
        "wrong": 0,
        "last_correct": false,
        "writing_correct": 0,
        "writing_wrong": 0,
        "writing_last_correct": false
    },
    {
        "word_id": "word_time",
        "hebrew": "זְמַן",
        "english": "time",
        "ukrainian": "час",
        "transcription": "zman",
        "correct": 0,
        "wrong": 0,
        "last_correct": false,
        "writing_correct": 0,
        "writing_wrong": 0,
        "writing_last_correct": false
    },
    {
        "word_id": "word_name",
        "hebrew": "שֵׁם",
        "english": "name",
        "ukrainian": "ім'я",
        "transcription": "shem",
        "correct": 0,
        "wrong": 0,
        "last_correct": false,
        "writing_correct": 0,
        "writing_wrong": 0,
        "writing_last_correct": false
    },
    {
        "word_id": "word_place",
        "hebrew": "מָקוֹם",
        "english": "place",
        "ukrainian": "місце",
        "transcription": "makom",
        "correct": 0,
        "wrong": 0,
        "last_correct": false,
        "writing_correct": 0,
        "writing_wrong": 0,
        "writing_last_correct": false
    },
    {
        "word_id": "word_work",
        "hebrew": "עֲבוֹדָה",
        "english": "work",
        "ukrainian": "робота",
        "transcription": "avoda",
        "correct": 0,
        "wrong": 0,
        "last_correct": false,
        "writing_correct": 0,
        "writing_wrong": 0,
        "writing_last_correct": false
    },
    {
        "word_id": "word_question",
        "hebrew": "שְׁאֵלָה",
        "english": "question",
        "ukrainian": "питання",
        "transcription": "she'ela",
        "correct": 0,
        "wrong": 0,
        "last_correct": false,
        "writing_correct": 0,
        "writing_wrong": 0,
        "writing_last_correct": false
    },
    {
        "word_id": "word_answer",
        "hebrew": "תְּשׁוּבָה",
        "english": "answer",
        "ukrainian": "відповідь",
        "transcription": "tshuva",
        "correct": 0,
        "wrong": 0,
        "last_correct": false,
        "writing_correct": 0,
        "writing_wrong": 0,
        "writing_last_correct": false
    },
    {
        "word_id": "word_story",
        "hebrew": "סִיפּוּר",
        "english": "story",
        "ukrainian": "історія",
        "transcription": "sipur",
        "correct": 0,
        "wrong": 0,
        "last_correct": false,
        "writing_correct": 0,
        "writing_wrong": 0,
        "writing_last_correct": false
    },
    {
        "word_id": "word_language",
        "hebrew": "שָׂפָה",
        "english": "language",
        "ukrainian": "мова",
        "transcription": "safa",
        "correct": 0,
        "wrong": 0,
        "last_correct": false,
        "writing_correct": 0,
        "writing_wrong": 0,
        "writing_last_correct": false
    },
    {
        "word_id": "word_word",
        "hebrew": "מִילָה",
        "english": "word",
        "ukrainian": "слово",
        "transcription": "mila",
        "correct": 0,
        "wrong": 0,
        "last_correct": false,
        "writing_correct": 0,
        "writing_wrong": 0,
        "writing_last_correct": false
    },
    {
        "word_id": "word_sentence",
        "hebrew": "מִשְׁפָּט",
        "english": "sentence",
        "ukrainian": "речення",
        "transcription": "mishpat",
        "correct": 0,
        "wrong": 0,
        "last_correct": false,
        "writing_correct": 0,
        "writing_wrong": 0,
        "writing_last_correct": false
    },
    {
        "word_id": "word_music",
        "hebrew": "מוּזִיקָה",
        "english": "music",
        "ukrainian": "музика",
        "transcription": "muzika",
        "correct": 0,
        "wrong": 0,
        "last_correct": false,
        "writing_correct": 0,
        "writing_wrong": 0,
        "writing_last_correct": false
    },
    {
        "word_id": "word_song",
        "hebrew": "שִׁיר",
        "english": "song",
        "ukrainian": "пісня",
        "transcription": "shir",
        "correct": 0,
        "wrong": 0,
        "last_correct": false,
        "writing_correct": 0,
        "writing_wrong": 0,
        "writing_last_correct": false
    },
    {
        "word_id": "word_movie",
        "hebrew": "סֶרֶט",
        "english": "movie",
        "ukrainian": "фільм",
        "transcription": "seret",
        "correct": 0,
        "wrong": 0,
        "last_correct": false,
        "writing_correct": 0,
        "writing_wrong": 0,
        "writing_last_correct": false
    },
    {
        "word_id": "word_picture",
        "hebrew": "תְּמוּנָה",
        "english": "picture",
        "ukrainian": "зображення",
        "transcription": "tmuna",
        "correct": 0,
        "wrong": 0,
        "last_correct": false,
        "writing_correct": 0,
        "writing_wrong": 0,
        "writing_last_correct": false
    },
    {
        "word_id": "word_bread",
        "hebrew": "לֶחֶם",
        "english": "bread",
        "ukrainian": "хліб",
        "transcription": "lechem",
        "correct": 0,
        "wrong": 0,
        "last_correct": false,
        "writing_correct": 0,
        "writing_wrong": 0,
        "writing_last_correct": false
    },
    {
        "word_id": "word_milk",
        "hebrew": "חָלָב",
        "english": "milk",
        "ukrainian": "молоко",
        "transcription": "chalav",
        "correct": 0,
        "wrong": 0,
        "last_correct": false,
        "writing_correct": 0,
        "writing_wrong": 0,
        "writing_last_correct": false
    },
    {
        "word_id": "word_coffee",
        "hebrew": "קָפֶה",
        "english": "coffee",
        "ukrainian": "кава",
        "transcription": "kafe",
        "correct": 0,
        "wrong": 0,
        "last_correct": false,
        "writing_correct": 0,
        "writing_wrong": 0,
        "writing_last_correct": false
    },
    {
        "word_id": "word_tea",
        "hebrew": "תֵּה",
        "english": "tea",
        "ukrainian": "чай",
        "transcription": "te",
        "correct": 0,
        "wrong": 0,
        "last_correct": false,
        "writing_correct": 0,
        "writing_wrong": 0,
        "writing_last_correct": false
    },
    {
        "word_id": "word_sugar",
        "hebrew": "סֻכָּר",
        "english": "sugar",
        "ukrainian": "цукор",
        "transcription": "sukar",
        "correct": 0,
        "wrong": 0,
        "last_correct": false,
        "writing_correct": 0,
        "writing_wrong": 0,
        "writing_last_correct": false
    },
    {
        "word_id": "word_salt",
        "hebrew": "מֶלַח",
        "english": "salt",
        "ukrainian": "сіль",
        "transcription": "melach",
        "correct": 0,
        "wrong": 0,
        "last_correct": false,
        "writing_correct": 0,
        "writing_wrong": 0,
        "writing_last_correct": false
    },
    {
        "word_id": "word_egg",
        "hebrew": "בֵּיצָה",
        "english": "egg",
        "ukrainian": "яйце",
        "transcription": "beitsa",
        "correct": 0,
        "wrong": 0,
        "last_correct": false,
        "writing_correct": 0,
        "writing_wrong": 0,
        "writing_last_correct": false
    },
    {
        "word_id": "word_cheese",
        "hebrew": "גְּבִינָה",
        "english": "cheese",
        "ukrainian": "сир",
        "transcription": "gvina",
        "correct": 0,
        "wrong": 0,
        "last_correct": false,
        "writing_correct": 0,
        "writing_wrong": 0,
        "writing_last_correct": false
    },
    {
        "word_id": "word_meat",
        "hebrew": "בָּשָׂר",
        "english": "meat",
        "ukrainian": "м'ясо",
        "transcription": "basar",
        "correct": 0,
        "wrong": 0,
        "last_correct": false,
        "writing_correct": 0,
        "writing_wrong": 0,
        "writing_last_correct": false
    },
    {
        "word_id": "word_fruit",
        "hebrew": "פְּרִי",
        "english": "fruit",
        "ukrainian": "фрукт",
        "transcription": "pri",
        "correct": 0,
        "wrong": 0,
        "last_correct": false,
        "writing_correct": 0,
        "writing_wrong": 0,
        "writing_last_correct": false
    },
    {
        "word_id": "word_kitchen",
        "hebrew": "מִטְבָּח",
        "english": "kitchen",
        "ukrainian": "кухня",
        "transcription": "mitbach",
        "correct": 0,
        "wrong": 0,
        "last_correct": false,
        "writing_correct": 0,
        "writing_wrong": 0,
        "writing_last_correct": false
    },
    {
        "word_id": "word_store",
        "hebrew": "חֲנוּת",
        "english": "store",
        "ukrainian": "магазин",
        "transcription": "chanut",
        "correct": 0,
        "wrong": 0,
        "last_correct": false,
        "writing_correct": 0,
        "writing_wrong": 0,
        "writing_last_correct": false
    },
    {
        "word_id": "word_market",
        "hebrew": "שׁוּק",
        "english": "market",
        "ukrainian": "ринок",
        "transcription": "shuk",
        "correct": 0,
        "wrong": 0,
        "last_correct": false,
        "writing_correct": 0,
        "writing_wrong": 0,
        "writing_last_correct": false
    },
    {
        "word_id": "word_bus",
        "hebrew": "אוֹטוֹבּוּס",
        "english": "bus",
        "ukrainian": "автобус",
        "transcription": "otobus",
        "correct": 0,
        "wrong": 0,
        "last_correct": false,
        "writing_correct": 0,
        "writing_wrong": 0,
        "writing_last_correct": false
    },
    {
        "word_id": "word_train",
        "hebrew": "רַכֶּבֶת",
        "english": "train",
        "ukrainian": "потяг",
        "transcription": "rakevet",
        "correct": 0,
        "wrong": 0,
        "last_correct": false,
        "writing_correct": 0,
        "writing_wrong": 0,
        "writing_last_correct": false
    },
    {
        "word_id": "word_station",
        "hebrew": "תַּחֲנָה",
        "english": "station",
        "ukrainian": "станція",
        "transcription": "tachana",
        "correct": 0,
        "wrong": 0,
        "last_correct": false,
        "writing_correct": 0,
        "writing_wrong": 0,
        "writing_last_correct": false
    },
    {
        "word_id": "word_road",
        "hebrew": "דֶּרֶךְ",
        "english": "road",
        "ukrainian": "дорога",
        "transcription": "derekh",
        "correct": 0,
        "wrong": 0,
        "last_correct": false,
        "writing_correct": 0,
        "writing_wrong": 0,
        "writing_last_correct": false
    },
    {
        "word_id": "word_room",
        "hebrew": "חֶדֶר",
        "english": "room",
        "ukrainian": "кімната",
        "transcription": "cheder",
        "correct": 0,
        "wrong": 0,
        "last_correct": false,
        "writing_correct": 0,
        "writing_wrong": 0,
        "writing_last_correct": false
    },
    {
        "word_id": "word_bed",
        "hebrew": "מִיטָּה",
        "english": "bed",
        "ukrainian": "ліжко",
        "transcription": "mita",
        "correct": 0,
        "wrong": 0,
        "last_correct": false,
        "writing_correct": 0,
        "writing_wrong": 0,
        "writing_last_correct": false
    },
    {
        "word_id": "word_bag",
        "hebrew": "תִּיק",
        "english": "bag",
        "ukrainian": "сумка",
        "transcription": "tik",
        "correct": 0,
        "wrong": 0,
        "last_correct": false,
        "writing_correct": 0,
        "writing_wrong": 0,
        "writing_last_correct": false
    },
    {
        "word_id": "word_shoe",
        "hebrew": "נַעַל",
        "english": "shoe",
        "ukrainian": "черевик",
        "transcription": "na'al",
        "correct": 0,
        "wrong": 0,
        "last_correct": false,
        "writing_correct": 0,
        "writing_wrong": 0,
        "writing_last_correct": false
    },
    {
        "word_id": "word_shirt",
        "hebrew": "חוּלְצָה",
        "english": "shirt",
        "ukrainian": "сорочка",
        "transcription": "chultsa",
        "correct": 0,
        "wrong": 0,
        "last_correct": false,
        "writing_correct": 0,
        "writing_wrong": 0,
        "writing_last_correct": false
    },
    {
        "word_id": "word_pants",
        "hebrew": "מִכְנָסַיִם",
        "english": "pants",
        "ukrainian": "штани",
        "transcription": "michnasayim",
        "correct": 0,
        "wrong": 0,
        "last_correct": false,
        "writing_correct": 0,
        "writing_wrong": 0,
        "writing_last_correct": false
    },
    {
        "word_id": "word_money",
        "hebrew": "כֶּסֶף",
        "english": "money",
        "ukrainian": "гроші",
        "transcription": "kesef",
        "correct": 0,
        "wrong": 0,
        "last_correct": false,
        "writing_correct": 0,
        "writing_wrong": 0,
        "writing_last_correct": false
    },
    {
        "word_id": "word_hand",
        "hebrew": "יָד",
        "english": "hand",
        "ukrainian": "рука",
        "transcription": "yad",
        "correct": 0,
        "wrong": 0,
        "last_correct": false,
        "writing_correct": 0,
        "writing_wrong": 0,
        "writing_last_correct": false
    },
    {
        "word_id": "word_head",
        "hebrew": "רֹאשׁ",
        "english": "head",
        "ukrainian": "голова",
        "transcription": "rosh",
        "correct": 0,
        "wrong": 0,
        "last_correct": false,
        "writing_correct": 0,
        "writing_wrong": 0,
        "writing_last_correct": false
    },
    {
        "word_id": "word_heart",
        "hebrew": "לֵב",
        "english": "heart",
        "ukrainian": "серце",
        "transcription": "lev",
        "correct": 0,
        "wrong": 0,
        "last_correct": false,
        "writing_correct": 0,
        "writing_wrong": 0,
        "writing_last_correct": false
    },
    {
        "word_id": "word_eye",
        "hebrew": "עַיִן",
        "english": "eye",
        "ukrainian": "око",
        "transcription": "ayin",
        "correct": 0,
        "wrong": 0,
        "last_correct": false,
        "writing_correct": 0,
        "writing_wrong": 0,
        "writing_last_correct": false
    },
    {
        "word_id": "word_face",
        "hebrew": "פָּנִים",
        "english": "face",
        "ukrainian": "обличчя",
        "transcription": "panim",
        "correct": 0,
        "wrong": 0,
        "last_correct": false,
        "writing_correct": 0,
        "writing_wrong": 0,
        "writing_last_correct": false
    },
    {
        "word_id": "word_body",
        "hebrew": "גּוּף",
        "english": "body",
        "ukrainian": "тіло",
        "transcription": "guf",
        "correct": 0,
        "wrong": 0,
        "last_correct": false,
        "writing_correct": 0,
        "writing_wrong": 0,
        "writing_last_correct": false
    },
    {
        "word_id": "word_sea",
        "hebrew": "יָם",
        "english": "sea",
        "ukrainian": "море",
        "transcription": "yam",
        "correct": 0,
        "wrong": 0,
        "last_correct": false,
        "writing_correct": 0,
        "writing_wrong": 0,
        "writing_last_correct": false
    },
    {
        "word_id": "word_rain",
        "hebrew": "גֶּשֶׁם",
        "english": "rain",
        "ukrainian": "дощ",
        "transcription": "geshem",
        "correct": 0,
        "wrong": 0,
        "last_correct": false,
        "writing_correct": 0,
        "writing_wrong": 0,
        "writing_last_correct": false
    },
    {
        "word_id": "word_wind",
        "hebrew": "רוּחַ",
        "english": "wind",
        "ukrainian": "вітер",
        "transcription": "ruach",
        "correct": 0,
        "wrong": 0,
        "last_correct": false,
        "writing_correct": 0,
        "writing_wrong": 0,
        "writing_last_correct": false
    },
    {
        "word_id": "word_fire",
        "hebrew": "אֵשׁ",
        "english": "fire",
        "ukrainian": "вогонь",
        "transcription": "esh",
        "correct": 0,
        "wrong": 0,
        "last_correct": false,
        "writing_correct": 0,
        "writing_wrong": 0,
        "writing_last_correct": false
    },
    {
        "word_id": "word_light",
        "hebrew": "אוֹר",
        "english": "light",
        "ukrainian": "світло",
        "transcription": "or",
        "correct": 0,
        "wrong": 0,
        "last_correct": false,
        "writing_correct": 0,
        "writing_wrong": 0,
        "writing_last_correct": false
    },
    {
        "word_id": "word_good",
        "hebrew": "טוֹב",
        "english": "good",
        "ukrainian": "добрий",
        "transcription": "tov",
        "correct": 0,
        "wrong": 0,
        "last_correct": false,
        "writing_correct": 0,
        "writing_wrong": 0,
        "writing_last_correct": false
    },
    {
        "word_id": "word_bad",
        "hebrew": "רַע",
        "english": "bad",
        "ukrainian": "поганий",
        "transcription": "ra",
        "correct": 0,
        "wrong": 0,
        "last_correct": false,
        "writing_correct": 0,
        "writing_wrong": 0,
        "writing_last_correct": false
    },
    {
        "word_id": "word_big",
        "hebrew": "גָּדוֹל",
        "english": "big",
        "ukrainian": "великий",
        "transcription": "gadol",
        "correct": 0,
        "wrong": 0,
        "last_correct": false,
        "writing_correct": 0,
        "writing_wrong": 0,
        "writing_last_correct": false
    },
    {
        "word_id": "word_small",
        "hebrew": "קָטָן",
        "english": "small",
        "ukrainian": "маленький",
        "transcription": "katan",
        "correct": 0,
        "wrong": 0,
        "last_correct": false,
        "writing_correct": 0,
        "writing_wrong": 0,
        "writing_last_correct": false
    },
    {
        "word_id": "word_new",
        "hebrew": "חָדָשׁ",
        "english": "new",
        "ukrainian": "новий",
        "transcription": "chadash",
        "correct": 0,
        "wrong": 0,
        "last_correct": false,
        "writing_correct": 0,
        "writing_wrong": 0,
        "writing_last_correct": false
    },
    {
        "word_id": "word_old",
        "hebrew": "יָשָׁן",
        "english": "old",
        "ukrainian": "старий",
        "transcription": "yashan",
        "correct": 0,
        "wrong": 0,
        "last_correct": false,
        "writing_correct": 0,
        "writing_wrong": 0,
        "writing_last_correct": false
    },
    {
        "word_id": "word_young",
        "hebrew": "צָעִיר",
        "english": "young",
        "ukrainian": "молодий",
        "transcription": "tsa'ir",
        "correct": 0,
        "wrong": 0,
        "last_correct": false,
        "writing_correct": 0,
        "writing_wrong": 0,
        "writing_last_correct": false
    },
    {
        "word_id": "word_beautiful",
        "hebrew": "יָפֶה",
        "english": "beautiful",
        "ukrainian": "гарний",
        "transcription": "yafe",
        "correct": 0,
        "wrong": 0,
        "last_correct": false,
        "writing_correct": 0,
        "writing_wrong": 0,
        "writing_last_correct": false
    },
    {
        "word_id": "word_long",
        "hebrew": "אָרוֹךְ",
        "english": "long",
        "ukrainian": "довгий",
        "transcription": "arokh",
        "correct": 0,
        "wrong": 0,
        "last_correct": false,
        "writing_correct": 0,
        "writing_wrong": 0,
        "writing_last_correct": false
    },
    {
        "word_id": "word_short",
        "hebrew": "קָצָר",
        "english": "short",
        "ukrainian": "короткий",
        "transcription": "katsar",
        "correct": 0,
        "wrong": 0,
        "last_correct": false,
        "writing_correct": 0,
        "writing_wrong": 0,
        "writing_last_correct": false
    },
    {
        "word_id": "word_high",
        "hebrew": "גָּבוֹהַּ",
        "english": "high",
        "ukrainian": "високий",
        "transcription": "gavoah",
        "correct": 0,
        "wrong": 0,
        "last_correct": false,
        "writing_correct": 0,
        "writing_wrong": 0,
        "writing_last_correct": false
    },
    {
        "word_id": "word_low",
        "hebrew": "נָמוּךְ",
        "english": "low",
        "ukrainian": "низький",
        "transcription": "namukh",
        "correct": 0,
        "wrong": 0,
        "last_correct": false,
        "writing_correct": 0,
        "writing_wrong": 0,
        "writing_last_correct": false
    },
    {
        "word_id": "word_hot",
        "hebrew": "חַם",
        "english": "hot",
        "ukrainian": "гарячий",
        "transcription": "cham",
        "correct": 0,
        "wrong": 0,
        "last_correct": false,
        "writing_correct": 0,
        "writing_wrong": 0,
        "writing_last_correct": false
    },
    {
        "word_id": "word_cold",
        "hebrew": "קַר",
        "english": "cold",
        "ukrainian": "холодний",
        "transcription": "kar",
        "correct": 0,
        "wrong": 0,
        "last_correct": false,
        "writing_correct": 0,
        "writing_wrong": 0,
        "writing_last_correct": false
    },
    {
        "word_id": "word_clean",
        "hebrew": "נָקִי",
        "english": "clean",
        "ukrainian": "чистий",
        "transcription": "naki",
        "correct": 0,
        "wrong": 0,
        "last_correct": false,
        "writing_correct": 0,
        "writing_wrong": 0,
        "writing_last_correct": false
    },
    {
        "word_id": "word_dirty",
        "hebrew": "מְלוּכְלָךְ",
        "english": "dirty",
        "ukrainian": "брудний",
        "transcription": "melukhlakh",
        "correct": 0,
        "wrong": 0,
        "last_correct": false,
        "writing_correct": 0,
        "writing_wrong": 0,
        "writing_last_correct": false
    },
    {
        "word_id": "word_fast",
        "hebrew": "מָהִיר",
        "english": "fast",
        "ukrainian": "швидкий",
        "transcription": "mahir",
        "correct": 0,
        "wrong": 0,
        "last_correct": false,
        "writing_correct": 0,
        "writing_wrong": 0,
        "writing_last_correct": false
    },
    {
        "word_id": "word_slow",
        "hebrew": "אִטִּי",
        "english": "slow",
        "ukrainian": "повільний",
        "transcription": "iti",
        "correct": 0,
        "wrong": 0,
        "last_correct": false,
        "writing_correct": 0,
        "writing_wrong": 0,
        "writing_last_correct": false
    },
    {
        "word_id": "word_strong",
        "hebrew": "חָזָק",
        "english": "strong",
        "ukrainian": "сильний",
        "transcription": "chazak",
        "correct": 0,
        "wrong": 0,
        "last_correct": false,
        "writing_correct": 0,
        "writing_wrong": 0,
        "writing_last_correct": false
    },
    {
        "word_id": "word_weak",
        "hebrew": "חַלָּשׁ",
        "english": "weak",
        "ukrainian": "слабкий",
        "transcription": "chalash",
        "correct": 0,
        "wrong": 0,
        "last_correct": false,
        "writing_correct": 0,
        "writing_wrong": 0,
        "writing_last_correct": false
    },
    {
        "word_id": "word_easy",
        "hebrew": "קַל",
        "english": "easy",
        "ukrainian": "легкий",
        "transcription": "kal",
        "correct": 0,
        "wrong": 0,
        "last_correct": false,
        "writing_correct": 0,
        "writing_wrong": 0,
        "writing_last_correct": false
    },
    {
        "word_id": "word_difficult",
        "hebrew": "קָשֶׁה",
        "english": "difficult",
        "ukrainian": "складний",
        "transcription": "kashe",
        "correct": 0,
        "wrong": 0,
        "last_correct": false,
        "writing_correct": 0,
        "writing_wrong": 0,
        "writing_last_correct": false
    },
    {
        "word_id": "word_happy",
        "hebrew": "שָׂמֵחַ",
        "english": "happy",
        "ukrainian": "щасливий",
        "transcription": "sameach",
        "correct": 0,
        "wrong": 0,
        "last_correct": false,
        "writing_correct": 0,
        "writing_wrong": 0,
        "writing_last_correct": false
    },
    {
        "word_id": "word_sad",
        "hebrew": "עָצוּב",
        "english": "sad",
        "ukrainian": "сумний",
        "transcription": "atzuv",
        "correct": 0,
        "wrong": 0,
        "last_correct": false,
        "writing_correct": 0,
        "writing_wrong": 0,
        "writing_last_correct": false
    },
    {
        "word_id": "word_important",
        "hebrew": "חָשׁוּב",
        "english": "important",
        "ukrainian": "важливий",
        "transcription": "chashuv",
        "correct": 0,
        "wrong": 0,
        "last_correct": false,
        "writing_correct": 0,
        "writing_wrong": 0,
        "writing_last_correct": false
    },
    {
        "word_id": "word_interesting",
        "hebrew": "מְעַנְיֵן",
        "english": "interesting",
        "ukrainian": "цікавий",
        "transcription": "me'anyen",
        "correct": 0,
        "wrong": 0,
        "last_correct": false,
        "writing_correct": 0,
        "writing_wrong": 0,
        "writing_last_correct": false
    },
    {
        "word_id": "word_open",
        "hebrew": "פָּתוּחַ",
        "english": "open",
        "ukrainian": "відкритий",
        "transcription": "patuach",
        "correct": 0,
        "wrong": 0,
        "last_correct": false,
        "writing_correct": 0,
        "writing_wrong": 0,
        "writing_last_correct": false
    },
    {
        "word_id": "word_closed",
        "hebrew": "סָגוּר",
        "english": "closed",
        "ukrainian": "закритий",
        "transcription": "sagur",
        "correct": 0,
        "wrong": 0,
        "last_correct": false,
        "writing_correct": 0,
        "writing_wrong": 0,
        "writing_last_correct": false
    },
    {
        "word_id": "word_full",
        "hebrew": "מָלֵא",
        "english": "full",
        "ukrainian": "повний",
        "transcription": "male",
        "correct": 0,
        "wrong": 0,
        "last_correct": false,
        "writing_correct": 0,
        "writing_wrong": 0,
        "writing_last_correct": false
    },
    {
        "word_id": "word_empty",
        "hebrew": "רֵיק",
        "english": "empty",
        "ukrainian": "порожній",
        "transcription": "reik",
        "correct": 0,
        "wrong": 0,
        "last_correct": false,
        "writing_correct": 0,
        "writing_wrong": 0,
        "writing_last_correct": false
    },
    {
        "word_id": "word_expensive",
        "hebrew": "יָקָר",
        "english": "expensive",
        "ukrainian": "дорогий",
        "transcription": "yakar",
        "correct": 0,
        "wrong": 0,
        "last_correct": false,
        "writing_correct": 0,
        "writing_wrong": 0,
        "writing_last_correct": false
    },
    {
        "word_id": "word_cheap",
        "hebrew": "זוֹל",
        "english": "cheap",
        "ukrainian": "дешевий",
        "transcription": "zol",
        "correct": 0,
        "wrong": 0,
        "last_correct": false,
        "writing_correct": 0,
        "writing_wrong": 0,
        "writing_last_correct": false
    },
    {
        "word_id": "word_about_with_regard_to_concerning",
        "hebrew": "אוֹדוֹת",
        "english": "about, with regard to, concerning",
        "ukrainian": "про; щодо, стосовно",
        "transcription": "odot",
        "correct": 0,
        "wrong": 0,
        "last_correct": false,
        "writing_correct": 0,
        "writing_wrong": 0,
        "writing_last_correct": false
    },
    {
        "word_id": "word_after",
        "hebrew": "אַחַר",
        "english": "after",
        "ukrainian": "після",
        "transcription": "achar",
        "correct": 0,
        "wrong": 0,
        "last_correct": false,
        "writing_correct": 0,
        "writing_wrong": 0,
        "writing_last_correct": false
    },
    {
        "word_id": "word_behind",
        "hebrew": "מֵאֲחוֹרֵי",
        "english": "behind",
        "ukrainian": "позаду, за",
        "transcription": "me'achorei",
        "correct": 0,
        "wrong": 0,
        "last_correct": false,
        "writing_correct": 0,
        "writing_wrong": 0,
        "writing_last_correct": false
    },
    {
        "word_id": "word_to_towards_into",
        "hebrew": "אֶל",
        "english": "to, towards, into",
        "ukrainian": "до, у напрямку, в",
        "transcription": "el",
        "correct": 1,
        "wrong": 0,
        "last_correct": false,
        "writing_correct": 0,
        "writing_wrong": 0,
        "writing_last_correct": false
    },
    {
        "word_id": "word_at_in_the_possession_of_near",
        "hebrew": "אֵצֶל",
        "english": "at, in the possession of; near",
        "ukrainian": "у, при; в когось, біля",
        "transcription": "etzel",
        "correct": 0,
        "wrong": 0,
        "last_correct": false,
        "writing_correct": 0,
        "writing_wrong": 0,
        "writing_last_correct": false
    },
    {
        "word_id": "word_used_before_a_definite_direct_object",
        "hebrew": "אֶת",
        "english": "(used before a definite direct object)",
        "ukrainian": "вживається перед означеним прямим додатком",
        "transcription": "et",
        "correct": 1,
        "wrong": 0,
        "last_correct": false,
        "writing_correct": 0,
        "writing_wrong": 0,
        "writing_last_correct": false
    },
    {
        "word_id": "word_in_by",
        "hebrew": "בְּ",
        "english": "in; by",
        "ukrainian": "у; за допомогою",
        "transcription": "be",
        "correct": 1,
        "wrong": 0,
        "last_correct": "2026-03-11T12:17:10",
        "writing_correct": 0,
        "writing_wrong": 0,
        "writing_last_correct": false
    },
    {
        "word_id": "word_by_means_of_using",
        "hebrew": "בְּאֶמְצָעוּת",
        "english": "by means of, using",
        "ukrainian": "за допомогою, використовуючи",
        "transcription": "be'emtza'ut",
        "correct": 0,
        "wrong": 0,
        "last_correct": false,
        "writing_correct": 0,
        "writing_wrong": 0,
        "writing_last_correct": false
    },
    {
        "word_id": "word_because_of_due_to",
        "hebrew": "בִּגְלַל",
        "english": "because of, due to",
        "ukrainian": "через, внаслідок",
        "transcription": "biglal",
        "correct": 0,
        "wrong": 0,
        "last_correct": false,
        "writing_correct": 0,
        "writing_wrong": 0,
        "writing_last_correct": false
    },
    {
        "word_id": "word_thanks_to_due_to_in_favour_of",
        "hebrew": "בִּזְכוּת",
        "english": "thanks to, due to; in favour of",
        "ukrainian": "завдяки; на користь",
        "transcription": "bizchut",
        "correct": 0,
        "wrong": 0,
        "last_correct": false,
        "writing_correct": 0,
        "writing_wrong": 0,
        "writing_last_correct": false
    },
    {
        "word_id": "word_between_amongst",
        "hebrew": "בֵּין",
        "english": "between, amongst",
        "ukrainian": "між, серед",
        "transcription": "ben",
        "correct": 0,
        "wrong": 0,
        "last_correct": false,
        "writing_correct": 0,
        "writing_wrong": 0,
        "writing_last_correct": false
    },
    {
        "word_id": "word_without",
        "hebrew": "בְּלִי",
        "english": "without",
        "ukrainian": "без",
        "transcription": "bli",
        "correct": 0,
        "wrong": 0,
        "last_correct": false,
        "writing_correct": 0,
        "writing_wrong": 0,
        "writing_last_correct": false
    },
    {
        "word_id": "word_during_over_the_course_of",
        "hebrew": "בְּמַהֲלַךְ",
        "english": "during, over the course of",
        "ukrainian": "протягом, упродовж",
        "transcription": "bemahalach",
        "correct": 0,
        "wrong": 0,
        "last_correct": false,
        "writing_correct": 0,
        "writing_wrong": 0,
        "writing_last_correct": false
    },
    {
        "word_id": "word_in_the_presence_of_somebody",
        "hebrew": "בְּמַעֲמַד",
        "english": "in the presence of (somebody)",
        "ukrainian": "у присутності (когось)",
        "transcription": "bema'amad",
        "correct": 0,
        "wrong": 0,
        "last_correct": false,
        "writing_correct": 0,
        "writing_wrong": 0,
        "writing_last_correct": false
    },
    {
        "word_id": "word_instead_of",
        "hebrew": "בִּמְקוֹם",
        "english": "instead of",
        "ukrainian": "замість",
        "transcription": "bimkom",
        "correct": 0,
        "wrong": 0,
        "last_correct": false,
        "writing_correct": 0,
        "writing_wrong": 0,
        "writing_last_correct": false
    },
    {
        "word_id": "word_for_in_favour_of_in_exchange_for_through_via_lit",
        "hebrew": "בַּעַד",
        "english": "for, in favour of; in exchange for; through, via (lit.)",
        "ukrainian": "за, на користь; в обмін на; через, за допомогою (книжн.)",
        "transcription": "ba'ad",
        "correct": 0,
        "wrong": 0,
        "last_correct": false,
        "writing_correct": 0,
        "writing_wrong": 0,
        "writing_last_correct": false
    },
    {
        "word_id": "word_following_as_a_result_of",
        "hebrew": "בְּעִקְבוֹת",
        "english": "following; in the wake of; as a result of, because of",
        "ukrainian": "слідом за; внаслідок, через",
        "transcription": "be'ikvot",
        "correct": 0,
        "wrong": 0,
        "last_correct": false,
        "writing_correct": 0,
        "writing_wrong": 0,
        "writing_last_correct": false
    },
    {
        "word_id": "word_facing_someone_in_the_face_of",
        "hebrew": "בִּפְנֵי",
        "english": "facing (someone); in the face of",
        "ukrainian": "перед (кимось); віч-на-віч з",
        "transcription": "bifnei",
        "correct": 0,
        "wrong": 0,
        "last_correct": false,
        "writing_correct": 0,
        "writing_wrong": 0,
        "writing_last_correct": false
    },
    {
        "word_id": "word_among_amidst_internally_on_the_inside",
        "hebrew": "בְּקֶרֶב",
        "english": "among, amidst; internally, on the inside",
        "ukrainian": "серед; усередині, всередині",
        "transcription": "bekerev",
        "correct": 1,
        "wrong": 0,
        "last_correct": "2026-03-11T12:17:03",
        "writing_correct": 0,
        "writing_wrong": 0,
        "writing_last_correct": false
    },
    {
        "word_id": "word_for_for_the_sake_of",
        "hebrew": "בִּשְׁבִיל",
        "english": "for, for the sake of",
        "ukrainian": "для, заради",
        "transcription": "bishvil",
        "correct": 0,
        "wrong": 0,
        "last_correct": false,
        "writing_correct": 0,
        "writing_wrong": 0,
        "writing_last_correct": false
    },
    {
        "word_id": "word_on_behalf_of_in_the_name_of",
        "hebrew": "בְּשֵׁם",
        "english": "on behalf of, in the name of",
        "ukrainian": "від імені, в ім'я",
        "transcription": "beshem",
        "correct": 0,
        "wrong": 0,
        "last_correct": false,
        "writing_correct": 0,
        "writing_wrong": 0,
        "writing_last_correct": false
    },
    {
        "word_id": "word_inside",
        "hebrew": "בְּתוֹךְ",
        "english": "inside",
        "ukrainian": "всередині",
        "transcription": "betoch",
        "correct": 0,
        "wrong": 0,
        "last_correct": false,
        "writing_correct": 0,
        "writing_wrong": 0,
        "writing_last_correct": false
    },
    {
        "word_id": "word_apart_from_other_than_beside",
        "hebrew": "זוּלַת",
        "english": "apart from, other than, beside",
        "ukrainian": "крім, окрім",
        "transcription": "zulat",
        "correct": 0,
        "wrong": 0,
        "last_correct": false,
        "writing_correct": 0,
        "writing_wrong": 0,
        "writing_last_correct": false
    },
    {
        "word_id": "word_as_like_in_the_role_of_about_approximately",
        "hebrew": "כְּ",
        "english": "as, like, in the role of; about, approximately",
        "ukrainian": "як, у ролі; приблизно, близько",
        "transcription": "ke",
        "correct": 1,
        "wrong": 0,
        "last_correct": "2026-03-26T16:24:35",
        "writing_correct": 0,
        "writing_wrong": 0,
        "writing_last_correct": false
    },
    {
        "word_id": "word_in_relation_to_vis_a_vis_towards",
        "hebrew": "כְּלַפֵּי",
        "english": "in relation to, vis-a-vis; towards",
        "ukrainian": "стосовно, щодо; до",
        "transcription": "klapei",
        "correct": 0,
        "wrong": 0,
        "last_correct": false,
        "writing_correct": 0,
        "writing_wrong": 0,
        "writing_last_correct": false
    },
    {
        "word_id": "word_like_as_similarly_to",
        "hebrew": "כְּמוֹ",
        "english": "like, as, similarly to",
        "ukrainian": "як, подібно до",
        "transcription": "kmo",
        "correct": 1,
        "wrong": 0,
        "last_correct": "2026-03-26T16:24:37",
        "writing_correct": 0,
        "writing_wrong": 0,
        "writing_last_correct": false
    },
    {
        "word_id": "word_like_as_literary",
        "hebrew": "כְּמוֹת",
        "english": "like, as (literary)",
        "ukrainian": "як (книжн.)",
        "transcription": "kmot",
        "correct": 0,
        "wrong": 0,
        "last_correct": false,
        "writing_correct": 0,
        "writing_wrong": 0,
        "writing_last_correct": false
    },
    {
        "word_id": "word_against_compared_to_as_opposed_to_in_exchange_for",
        "hebrew": "כְּנֶגֶד",
        "english": "against; compared to, as opposed to; in exchange for",
        "ukrainian": "проти; порівняно з, на відміну від; в обмін на",
        "transcription": "keneged",
        "correct": 1,
        "wrong": 1,
        "last_correct": false,
        "writing_correct": 0,
        "writing_wrong": 0,
        "writing_last_correct": false
    },
    {
        "word_id": "word_to_for_of_indicating_possession_with",
        "hebrew": "לְ",
        "english": "to; for; of (indicating possession, with יש/אין)",
        "ukrainian": "до; для; у, в (позначення належності з יש/אין)",
        "transcription": "le",
        "correct": 0,
        "wrong": 0,
        "last_correct": false,
        "writing_correct": 0,
        "writing_wrong": 0,
        "writing_last_correct": false
    },
    {
        "word_id": "word_along_throughout",
        "hebrew": "לְאוֹרֶךְ",
        "english": "along, throughout",
        "ukrainian": "уздовж, протягом",
        "transcription": "le'orech",
        "correct": 0,
        "wrong": 0,
        "last_correct": false,
        "writing_correct": 0,
        "writing_wrong": 0,
        "writing_last_correct": false
    },
    {
        "word_id": "word_regarding_concerning",
        "hebrew": "לְגַבֵּי",
        "english": "regarding, concerning",
        "ukrainian": "щодо, стосовно",
        "transcription": "legabei",
        "correct": 0,
        "wrong": 0,
        "last_correct": false,
        "writing_correct": 0,
        "writing_wrong": 0,
        "writing_last_correct": false
    },
    {
        "word_id": "word_according_to_also",
        "hebrew": "לְדִבְרֵי",
        "english": "according to (also לדבריו/ה של...)",
        "ukrainian": "за словами, згідно з (також לדבריו/ה של...)",
        "transcription": "ledivrei",
        "correct": 0,
        "wrong": 0,
        "last_correct": false,
        "writing_correct": 0,
        "writing_wrong": 0,
        "writing_last_correct": false
    },
    {
        "word_id": "word_near_next_to",
        "hebrew": "לְיַד",
        "english": "near, next to",
        "ukrainian": "біля, поруч із",
        "transcription": "leyad",
        "correct": 0,
        "wrong": 0,
        "last_correct": false,
        "writing_correct": 0,
        "writing_wrong": 0,
        "writing_last_correct": false
    },
    {
        "word_id": "word_into_the_hands_of_to_over_to_for_to_the_attention_of",
        "hebrew": "לִידֵי",
        "english": "into the hands of; to, over to, for, to the attention of",
        "ukrainian": "до рук; до, комусь, на розгляд",
        "transcription": "lidei",
        "correct": 1,
        "wrong": 0,
        "last_correct": false,
        "writing_correct": 0,
        "writing_wrong": 0,
        "writing_last_correct": false
    },
    {
        "word_id": "word_for_the_sake_of_for_the_benefit_of_in_order_to_so_that_lit",
        "hebrew": "לְמַעַן",
        "english": "for the sake of, for the benefit of; in order to, so that (lit.)",
        "ukrainian": "заради, на благо; щоб, аби (книжн.)",
        "transcription": "lema'an",
        "correct": 0,
        "wrong": 0,
        "last_correct": false,
        "writing_correct": 0,
        "writing_wrong": 0,
        "writing_last_correct": false
    },
    {
        "word_id": "word_according_to",
        "hebrew": "לְפִי",
        "english": "according to",
        "ukrainian": "згідно з, за",
        "transcription": "lefi",
        "correct": 0,
        "wrong": 0,
        "last_correct": false,
        "writing_correct": 0,
        "writing_wrong": 0,
        "writing_last_correct": false
    },
    {
        "word_id": "word_before_in_front_of",
        "hebrew": "לִפְנֵי",
        "english": "before, in front of",
        "ukrainian": "перед, попереду",
        "transcription": "lifnei",
        "correct": 0,
        "wrong": 0,
        "last_correct": false,
        "writing_correct": 0,
        "writing_wrong": 0,
        "writing_last_correct": false
    },
    {
        "word_id": "word_towards_forward_to_for_in_preparation_to",
        "hebrew": "לִקְרַאת",
        "english": "towards, forward to, for, in preparation to",
        "ukrainian": "до, назустріч; для, напередодні",
        "transcription": "likrat",
        "correct": 0,
        "wrong": 0,
        "last_correct": false,
        "writing_correct": 0,
        "writing_wrong": 0,
        "writing_last_correct": false
    },
    {
        "word_id": "word_across",
        "hebrew": "לְרוֹחַב",
        "english": "across",
        "ukrainian": "впоперек, через",
        "transcription": "lerochav",
        "correct": 0,
        "wrong": 0,
        "last_correct": false,
        "writing_correct": 0,
        "writing_wrong": 0,
        "writing_last_correct": false
    },
    {
        "word_id": "word_against_opposite_in_front_of",
        "hebrew": "מוּל",
        "english": "against; opposite, in front of",
        "ukrainian": "навпроти; проти, перед",
        "transcription": "mul",
        "correct": 0,
        "wrong": 0,
        "last_correct": false,
        "writing_correct": 0,
        "writing_wrong": 0,
        "writing_last_correct": false
    },
    {
        "word_id": "word_from_of_than_compared_to",
        "hebrew": "מִן",
        "english": "from, of; than, compared to",
        "ukrainian": "з, від; ніж, порівняно з",
        "transcription": "min",
        "correct": 1,
        "wrong": 0,
        "last_correct": false,
        "writing_correct": 0,
        "writing_wrong": 0,
        "writing_last_correct": false
    },
    {
        "word_id": "word_above_over_on_top_of",
        "hebrew": "מֵעַל",
        "english": "above, over; on top of",
        "ukrainian": "над, зверху на",
        "transcription": "me'al",
        "correct": 1,
        "wrong": 0,
        "last_correct": false,
        "writing_correct": 0,
        "writing_wrong": 0,
        "writing_last_correct": false
    },
    {
        "word_id": "word_from_away_from_because_with",
        "hebrew": "מִפְּנֵי",
        "english": "from, away from; because (with ש־)",
        "ukrainian": "від, з; тому що (з ש־)",
        "transcription": "mipnei",
        "correct": 0,
        "wrong": 0,
        "last_correct": false,
        "writing_correct": 0,
        "writing_wrong": 0,
        "writing_last_correct": false
    },
    {
        "word_id": "word_under_below",
        "hebrew": "מִתַּחַת",
        "english": "under, below",
        "ukrainian": "під, нижче",
        "transcription": "mitachat",
        "correct": 0,
        "wrong": 0,
        "last_correct": false,
        "writing_correct": 0,
        "writing_wrong": 0,
        "writing_last_correct": false
    },
    {
        "word_id": "word_against",
        "hebrew": "נֶגֶד",
        "english": "against",
        "ukrainian": "проти",
        "transcription": "neged",
        "correct": 0,
        "wrong": 0,
        "last_correct": false,
        "writing_correct": 0,
        "writing_wrong": 0,
        "writing_last_correct": false
    },
    {
        "word_id": "word_for",
        "hebrew": "עֲבוּר",
        "english": "for",
        "ukrainian": "для, заради",
        "transcription": "avur",
        "correct": 0,
        "wrong": 0,
        "last_correct": false,
        "writing_correct": 0,
        "writing_wrong": 0,
        "writing_last_correct": false
    },
    {
        "word_id": "word_until_up_to",
        "hebrew": "עַד",
        "english": "until, up to",
        "ukrainian": "до, аж до",
        "transcription": "ad",
        "correct": 0,
        "wrong": 0,
        "last_correct": false,
        "writing_correct": 0,
        "writing_wrong": 0,
        "writing_last_correct": false
    },
    {
        "word_id": "word_on_upon_over_about_regarding",
        "hebrew": "עַל",
        "english": "on, upon; over; about, regarding",
        "ukrainian": "на; над; про, щодо",
        "transcription": "al",
        "correct": 0,
        "wrong": 0,
        "last_correct": false,
        "writing_correct": 0,
        "writing_wrong": 0,
        "writing_last_correct": false
    },
    {
        "word_id": "word_on_upon",
        "hebrew": "עַל גַּב",
        "english": "on the back of",
        "ukrainian": "на спинці, на задній частині",
        "transcription": "al gav",
        "correct": 0,
        "wrong": 0,
        "last_correct": false,
        "writing_correct": 0,
        "writing_wrong": 0,
        "writing_last_correct": false
    },
    {
        "word_id": "word_on_upon_al_gabei",
        "hebrew": "עַל גַּבֵּי",
        "english": "on, atop; on top of",
        "ukrainian": "на, зверху на",
        "transcription": "al gabei",
        "correct": 0,
        "wrong": 0,
        "last_correct": false,
        "writing_correct": 0,
        "writing_wrong": 0,
        "writing_last_correct": false
    },
    {
        "word_id": "word_next_to",
        "hebrew": "עַל יַד",
        "english": "next to",
        "ukrainian": "поруч із, біля",
        "transcription": "al yad",
        "correct": 0,
        "wrong": 0,
        "last_correct": false,
        "writing_correct": 0,
        "writing_wrong": 0,
        "writing_last_correct": false
    },
    {
        "word_id": "word_by_via_in_a_passive_construction_by_means_of",
        "hebrew": "עַל יְדֵי",
        "english": "by, via (in a passive construction); by means of",
        "ukrainian": "кимось, через (у пасивній конструкції); за допомогою",
        "transcription": "al yedei",
        "correct": 0,
        "wrong": 0,
        "last_correct": false,
        "writing_correct": 0,
        "writing_wrong": 0,
        "writing_last_correct": false
    },
    {
        "word_id": "word_according_to_in_accordance_with",
        "hebrew": "עַל פִּי",
        "english": "according to, in accordance with",
        "ukrainian": "згідно з, відповідно до",
        "transcription": "al pi",
        "correct": 0,
        "wrong": 0,
        "last_correct": false,
        "writing_correct": 0,
        "writing_wrong": 0,
        "writing_last_correct": false
    },
    {
        "word_id": "word_over_on_the_surface_of_above",
        "hebrew": "עַל פְּנֵי",
        "english": "over, on the surface of; above",
        "ukrainian": "над, по поверхні; поверх",
        "transcription": "al pnei",
        "correct": 0,
        "wrong": 0,
        "last_correct": false,
        "writing_correct": 0,
        "writing_wrong": 0,
        "writing_last_correct": false
    },
    {
        "word_id": "word_with_forms_etc_are_literary",
        "hebrew": "עִם",
        "english": "with (forms עימי, עימו etc. are literary)",
        "ukrainian": "з (форми עימי, עימו тощо є книжними)",
        "transcription": "im",
        "correct": 0,
        "wrong": 1,
        "last_correct": false,
        "writing_correct": 0,
        "writing_wrong": 0,
        "writing_last_correct": false
    },
    {
        "word_id": "word_compared_with",
        "hebrew": "לְעוּמַּת",
        "english": "compared with",
        "ukrainian": "порівняно з",
        "transcription": "le'umat",
        "correct": 0,
        "wrong": 0,
        "last_correct": false,
        "writing_correct": 0,
        "writing_wrong": 0,
        "writing_last_correct": false
    },
    {
        "word_id": "word_of_belonging_to",
        "hebrew": "שֶׁל",
        "english": "of, belonging to",
        "ukrainian": "чий, належний",
        "transcription": "shel",
        "correct": 0,
        "wrong": 0,
        "last_correct": false,
        "writing_correct": 0,
        "writing_wrong": 0,
        "writing_last_correct": false
    },
    {
        "word_id": "word_under_below_beneath_in_exchange_for",
        "hebrew": "תַּחַת",
        "english": "under, below, beneath; in exchange for",
        "ukrainian": "під, нижче, під самим; в обмін на",
        "transcription": "tachat",
        "correct": 0,
        "wrong": 0,
        "last_correct": false,
        "writing_correct": 0,
        "writing_wrong": 0,
        "writing_last_correct": false
    }
]
